zzlib/__init__.py
zzlib/cls.py
zzlib/func.py
zzlib/mixin.py
zzlib/utils.py
zzlib/bio/seq.py
zzlib/cli/__init__.py
zzlib/cli/progress.py
zzlib/cli/click/__init__.py
zzlib/cli/click/_common.py
zzlib/cli/click/_shared_option.py
zzlib/cli/typer/__init__.py
zzlib/cli/typer/_async.py
zzlib/cli/typer/_optional_value.py
zzlib/data/__init__.py
zzlib/data/pandas.py
zzlib/data/utils.py
zzlib/dl/__init__.py
zzlib/dl/device.py
zzlib/log/__init__.py
zzlib/log/chameleon.py
zzlib/log/common.py
zzlib/log/logging.py
zzlib/log/loguru.py
zzlib/sch/__init__.py
zzlib/sch/files.py
zzlib/sch/structure.py
zzlib/sch/utils.py
zzlib/sch/workflow.py
zzlib/shell/__init__.py
zzlib/shell/env.py
zzlib/shell/envmgr.py
zzlib/shell/pathutils.py
zzlib/shell/sandbox.py
zzlib/shell/shell.py
zzlib/shell/slurm.py
zzlib/shell/subprocess.py
zzlib-0.1.2.dist-info/METADATA
zzlib-0.1.2.dist-info/WHEEL
zzlib-0.1.2.dist-info/RECORD
